modelv1/tools/__init__.py
modelv1/tools/dump_model.py
modelv1/tools/export_model.py
modelv1/tools/import_model.py
modelv1/tools/sync_model.py
modelv1/tools/update_metadata.py
modelv1/toolsv2/__init__.py
modelv1/toolsv2/export_model.py
modelv1/toolsv2/import_model.py
windmillmodelv1/__init__.py
windmillmodelv1/client/__init__.py
windmillmodelv1/client/model_api_model.py
windmillmodelv1/client/model_api_modelstore.py
windmillmodelv1/client/model_client.py
windmillmodelv1/graph/__init__.py
windmillmodelv1/graph/graph.py
windmillmodelv1/metadata/__init__.py
windmillmodelv1/metadata/metadata.py
windmillmodelv1/tools/__init__.py
windmillmodelv1/tools/dump_model.py
windmillmodelv1/tools/export_model.py
windmillmodelv1/tools/import_model.py
windmillmodelv1/tools/sync_model.py
windmillmodelv1/tools/update_metadata.py
windmillmodelv1/toolsv2/__init__.py
windmillmodelv1/toolsv2/export_model.py
windmillmodelv1/toolsv2/import_model.py
windmill_model-1.0.0.60.dist-info/METADATA
windmill_model-1.0.0.60.dist-info/WHEEL
windmill_model-1.0.0.60.dist-info/top_level.txt
windmill_model-1.0.0.60.dist-info/RECORD
